.dockerignore
.gitignore
CHANGELOG.md
Dockerfile
LICENSE
MANIFEST.in
README.md
requirements.txt
setup.py
.github/workflows/deploy.yml
.github/workflows/main.yml
juliart/__init__.py
juliart/client.py
juliart/colors.py
juliart/main.py
juliart/namer.py
juliart/utils.py
juliart/version.py
juliart.egg-info/PKG-INFO
juliart.egg-info/SOURCES.txt
juliart.egg-info/dependency_links.txt
juliart.egg-info/entry_points.txt
juliart.egg-info/not-zip-safe
juliart.egg-info/requires.txt
juliart.egg-info/top_level.txt
juliart/fonts/OpenSans-Regular.ttf
juliart/fonts/Pacifico-Regular.ttf